nuvolos_client_api/__init__.py
nuvolos_client_api/api_client.py
nuvolos_client_api/api_response.py
nuvolos_client_api/configuration.py
nuvolos_client_api/exceptions.py
nuvolos_client_api/py.typed
nuvolos_client_api/rest.py
nuvolos_client_api/api/__init__.py
nuvolos_client_api/api/apps_v1_api.py
nuvolos_client_api/api/distribution_v1_api.py
nuvolos_client_api/api/files_v1_api.py
nuvolos_client_api/api/instances_v1_api.py
nuvolos_client_api/api/organizations_v1_api.py
nuvolos_client_api/api/snapshots_v1_api.py
nuvolos_client_api/api/spaces_v1_api.py
nuvolos_client_api/api/tables_v1_api.py
nuvolos_client_api/api/tasks_v1_api.py
nuvolos_client_api/api/workloads_v1_api.py
nuvolos_client_api/models/__init__.py
nuvolos_client_api/models/api_node_pool.py
nuvolos_client_api/models/application.py
nuvolos_client_api/models/client_api_error.py
nuvolos_client_api/models/column_public.py
nuvolos_client_api/models/ddl.py
nuvolos_client_api/models/distribution_request.py
nuvolos_client_api/models/execute_command.py
nuvolos_client_api/models/execute_command_response.py
nuvolos_client_api/models/file_public.py
nuvolos_client_api/models/instance.py
nuvolos_client_api/models/org.py
nuvolos_client_api/models/snapshot.py
nuvolos_client_api/models/snapshot_create_request.py
nuvolos_client_api/models/space.py
nuvolos_client_api/models/start_app.py
nuvolos_client_api/models/table.py
nuvolos_client_api/models/table_update.py
nuvolos_client_api/models/task.py
nuvolos_client_api/models/task1.py
nuvolos_client_api/models/workload_detailed.py
nuvolos_client_api-1.3.0.dist-info/METADATA
nuvolos_client_api-1.3.0.dist-info/WHEEL
nuvolos_client_api-1.3.0.dist-info/top_level.txt
nuvolos_client_api-1.3.0.dist-info/RECORD
