Metadata-Version: 2.4
Name: nuvolos-client-api
Version: 1.3.0
Summary: Nuvolos
Home-page: https://www.nuvolos.cloud
Author: The Nuvolos Team
Author-email: support@nuvolos.cloud
Keywords: OpenAPI,OpenAPI-Generator,Nuvolos
Requires-Dist: urllib3<3.0.0,>=2.1.0
Requires-Dist: python-dateutil>=2.8.2
Requires-Dist: pydantic>=2
Requires-Dist: typing-extensions>=4.7.1
Dynamic: author
Dynamic: author-email
Dynamic: description
Dynamic: description-content-type
Dynamic: home-page
Dynamic: keywords
Dynamic: requires-dist
Dynamic: summary
